smb_backup/__init__.py
smb_backup-0.0.3.dist-info/LICENSE
smb_backup-0.0.3.dist-info/METADATA
smb_backup-0.0.3.dist-info/WHEEL
smb_backup-0.0.3.dist-info/top_level.txt
smb_backup-0.0.3.dist-info/RECORD
