Metadata-Version: 2.1
Name: smb-backup
Version: 0.0.3
Summary: Backup directories to an SMB drive
Author: Lukas Kreussel
License: MIT License        
Project-URL: Homepage, https://github.com/LLukas22/python-smb-backup
Project-URL: Bug Tracker, https://github.com/LLukas22/python-smb-backup/issues
Classifier: Programming Language :: Python :: 3
Classifier: License :: OSI Approved :: MIT License
Classifier: Operating System :: OS Independent
Requires-Python: >=3.10
License-File: LICENSE
Requires-Dist: smbprotocol (>=1.9.0)
